bifrost/__init__.py
bifrost/cli.py
bifrost/inventory.py
bifrost/version.py
bifrost/tests/__init__.py
bifrost/tests/base.py
bifrost/tests/utils.py
bifrost/tests/functional/__init__.py
bifrost/tests/functional/test_inventory_functional.py
bifrost/tests/unit/__init__.py
bifrost/tests/unit/test_cli.py
bifrost/tests/unit/test_inventory.py
bifrost/tests/unit/test_network_metadata.py
bifrost-19.3.0.dist-info/AUTHORS
bifrost-19.3.0.dist-info/LICENSE
bifrost-19.3.0.dist-info/METADATA
bifrost-19.3.0.dist-info/WHEEL
bifrost-19.3.0.dist-info/entry_points.txt
bifrost-19.3.0.dist-info/pbr.json
bifrost-19.3.0.dist-info/top_level.txt
bifrost-19.3.0.dist-info/RECORD
